mkrTree/__init__.py
mkrTree/objs.py
mkrTree/rander.py
mkrTree/tree.py
mkrTree-0.1.0.dist-info/LICENCE.txt
mkrTree-0.1.0.dist-info/METADATA
mkrTree-0.1.0.dist-info/WHEEL
mkrTree-0.1.0.dist-info/top_level.txt
mkrTree-0.1.0.dist-info/RECORD
